random_useragent/__init__.py
random_useragent/android.py
random_useragent/chrome.py
random_useragent/iphone.py
random_useragent/linux.py
random_useragent/mac.py
random_useragent/useragent.py
random_useragent/windows.py
r_useragent-1.1.dist-info/LICENSE
r_useragent-1.1.dist-info/METADATA
r_useragent-1.1.dist-info/WHEEL
r_useragent-1.1.dist-info/top_level.txt
r_useragent-1.1.dist-info/RECORD
