Metadata-Version: 2.1
Name: r_useragent
Version: 1.1
Summary: generate random user-agent
Author-email: saucerman <gyq0929@gmail.com>
Project-URL: Homepage, https://github.com/saucer-man/random-useragent
Project-URL: Bug Tracker, https://github.com/saucer-man/random-useragent/issues
Classifier: Programming Language :: Python :: 3
Requires-Python: >=3.6
License-File: LICENSE
